talon_one/__init__.py
talon_one/api_client.py
talon_one/configuration.py
talon_one/exceptions.py
talon_one/rest.py
talon_one/api/__init__.py
talon_one/api/integration_api.py
talon_one/api/management_api.py
talon_one/models/__init__.py
talon_one/models/accept_coupon_effect_props.py
talon_one/models/accept_referral_effect_props.py
talon_one/models/access_log_entry.py
talon_one/models/account.py
talon_one/models/account_additional_cost.py
talon_one/models/account_analytics.py
talon_one/models/account_dashboard_statistic.py
talon_one/models/account_dashboard_statistic_campaigns.py
talon_one/models/account_dashboard_statistic_discount.py
talon_one/models/account_dashboard_statistic_loyalty_points.py
talon_one/models/account_dashboard_statistic_referrals.py
talon_one/models/account_dashboard_statistic_revenue.py
talon_one/models/account_entity.py
talon_one/models/account_limits.py
talon_one/models/achievement.py
talon_one/models/achievement_additional_properties.py
talon_one/models/achievement_base.py
talon_one/models/achievement_progress.py
talon_one/models/achievement_progress_with_definition.py
talon_one/models/achievement_status_entry.py
talon_one/models/add_free_item_effect_props.py
talon_one/models/add_item_catalog_action.py
talon_one/models/add_loyalty_points.py
talon_one/models/add_loyalty_points_effect_props.py
talon_one/models/add_price_adjustment_catalog_action.py
talon_one/models/add_to_audience_effect_props.py
talon_one/models/added_deducted_points_balances_notification_policy.py
talon_one/models/added_deducted_points_notification_policy.py
talon_one/models/additional_campaign_properties.py
talon_one/models/additional_cost.py
talon_one/models/analytics_data_point.py
talon_one/models/analytics_data_point_with_trend.py
talon_one/models/analytics_data_point_with_trend_and_influenced_rate.py
talon_one/models/analytics_data_point_with_trend_and_uplift.py
talon_one/models/analytics_product.py
talon_one/models/analytics_sku.py
talon_one/models/api_error.py
talon_one_python_sdk-9.0.0.dist-info/licenses/LICENSE
talon_one_python_sdk-9.0.0.dist-info/METADATA
talon_one_python_sdk-9.0.0.dist-info/WHEEL
talon_one_python_sdk-9.0.0.dist-info/top_level.txt
talon_one_python_sdk-9.0.0.dist-info/RECORD
