Metadata-Version: 2.4
Name: talon-one-python-sdk
Version: 9.0.0
Summary: Talon.One Python SDK
Home-page: https://github.com/talon-one/talon_one.py/
Author: Talon.One GmbH
Author-email: devs@talon.one
License: MIT
Keywords: talon,one,sdk
License-File: LICENSE
Requires-Dist: urllib3>=1.15
Requires-Dist: six>=1.10
Requires-Dist: certifi
Requires-Dist: python-dateutil
Dynamic: author
Dynamic: author-email
Dynamic: description
Dynamic: description-content-type
Dynamic: home-page
Dynamic: keywords
Dynamic: license
Dynamic: license-file
Dynamic: requires-dist
Dynamic: summary
